LICENSE
slk/__init__.py
slk/chain/__init__.py
slk/chain/asset_aliases.py
slk/chain/chain.py
slk/chain/chain_setup.py
slk/chain/context_managers.py
slk/chain/external_chain.py
slk/chain/external_node.py
slk/chain/key_manager.py
slk/chain/mainchain.py
slk/chain/node.py
slk/chain/sidechain.py
slk/chain/xchain_transfer.py
slk/classes/__init__.py
slk/classes/account.py
slk/classes/config_file.py
slk/config/__init__.py
slk/config/config_params.py
slk/config/create_config_files.py
slk/config/helper_classes.py
slk/config/network.py
slk/config/templates/mainchain_standalone.jinja
slk/config/templates/sidechain.jinja
slk/config/templates/validators.jinja
slk/repl/__init__.py
slk/repl/repl.py
slk/repl/repl_functionality.py
slk/run_shell.py
slk/sidechain_interaction.py
slk/sidechain_params.py
slk/utils/__init__.py
slk/utils/eprint.py
slk/utils/log_analyzer.py
sidechain_launch_kit-1.0.0b1.dist-info/entry_points.txt
sidechain_launch_kit-1.0.0b1.dist-info/LICENSE
sidechain_launch_kit-1.0.0b1.dist-info/WHEEL
sidechain_launch_kit-1.0.0b1.dist-info/METADATA
sidechain_launch_kit-1.0.0b1.dist-info/RECORD
