Metadata-Version: 2.1
Name: sidechain-launch-kit
Version: 1.0.0b1
Summary: Python scripts to tests and explore side chains
Home-page: https://github.com/xpring-eng/sidechain-launch-kit
License: MIT
Keywords: xrp,xrpl,cryptocurrency,blockchain,sidechain
Author: Mayukha Vadari
Author-email: mvadari@ripple.com
Requires-Python: >=3.8,<3.10
Classifier: License :: OSI Approved :: MIT License
Classifier: Programming Language :: Python :: 3
Classifier: Programming Language :: Python :: 3.8
Classifier: Programming Language :: Python :: 3.9
Requires-Dist: Jinja2 (>=3.0.3,<4.0.0)
Requires-Dist: pytest (>=6.2.5,<7.0.0)
Requires-Dist: python-dotenv (>=0.19.1,<0.20.0)
Requires-Dist: tabulate (>=0.8.9,<0.9.0)
Requires-Dist: websockets (>=9.1,<10.0)
Requires-Dist: xrpl-py (>=1.3.0,<2.0.0)
Project-URL: Repository, https://github.com/xpring-eng/sidechain-launch-kit
